{
  "project_info": {
    "project_number": "185630036316",
    "project_id": "task-hub-e1fe2",
    "storage_bucket": "task-hub-e1fe2.appspot.com"
  },
  "client": [
    {
      "client_info": {
        "mobilesdk_app_id": "1:185630036316:android:40f564aa6a1922d7a8b199",
        "android_client_info": {
          "package_name": "com.example.task_manager"
        }
      },
      "oauth_client": [
        {
          "client_id": "185630036316-ij5rp30mdkmvc3d2iaabdohbbgmn6hf8.apps.googleusercontent.com",
          "client_type": 1,
          "android_info": {
            "package_name": "com.example.task_manager",
            "certificate_hash": "ce0cb037794f7c95763a88e7605a8500b9604243"
          }
        },
        {
          "client_id": "185630036316-2dp01nuf8tlcf6ogl0htp2hv8sevqupr.apps.googleusercontent.com",
          "client_type": 3
        }
      ],
      "api_key": [
        {
          "current_key": "AIzaSyCz3WYIQs1KnCc_6vWe16vx5neXYxcXW1w"
        }
      ],
      "services": {
        "appinvite_service": {
          "other_platform_oauth_client": [
            {
              "client_id": "185630036316-2dp01nuf8tlcf6ogl0htp2hv8sevqupr.apps.googleusercontent.com",
              "client_type": 3
            }
          ]
        }
      }
    }
  ],
  "configuration_version": "1"
}